UzTransliterator/UzTransliterator.py
UzTransliterator/__init__.py
UzTransliterator/cyr_exwords.csv
UzTransliterator/lat_exwords.csv
UzTransliterator/test.py
UzTransliterator-0.0.35.dist-info/LICENSE
UzTransliterator-0.0.35.dist-info/METADATA
UzTransliterator-0.0.35.dist-info/WHEEL
UzTransliterator-0.0.35.dist-info/top_level.txt
UzTransliterator-0.0.35.dist-info/RECORD
