Metadata-Version: 2.1
Name: UzTransliterator
Version: 0.0.35
Summary: UzTransliterator | Transliteration tool for Uzbek language - Cyrillic<>Latin<>NewLatin
Home-page: https://github.com/UlugbekSalaev/UzTransliterator
Author: Ulugbek Salaev, Elmurod Kuriyozov
Author-email: ulugbek0302@gmail.com, e.kuriyozov@udc.es
License: UNKNOWN
Project-URL: Bug Tracker, https://github.com/UlugbekSalaev/UzTransliterator/issues
Keywords: python,transliteration,uzbek-language,cyrillic,latin
Platform: UNKNOWN
Classifier: Programming Language :: Python :: 3
Classifier: License :: OSI Approved :: MIT License
Classifier: Operating System :: OS Independent
Requires-Python: >=3.6
License-File: LICENSE
